Metadata-Version: 2.4
Name: ovos-stt-plugin-whispercppserver
Version: 0.0.1
Summary: ovos stt plugin for whisper.cpp server
Home-page: https://github.com/ser/ovos-stt-whispercppserver-plugin
Author: ser
Author-email: ovos+github@sergevictor.eu
License: Apache-2.0
Keywords: mycroft OpenVoiceOS OVOS plugin stt whisper.cpp whisper
Classifier: Development Status :: 3 - Alpha
Classifier: Intended Audience :: Developers
Classifier: Topic :: Text Processing :: Linguistic
Classifier: Programming Language :: Python :: 3.7
Classifier: Programming Language :: Python :: 3.8
Classifier: Programming Language :: Python :: 3.9
Classifier: Programming Language :: Python :: 3.10
Classifier: Programming Language :: Python :: 3.11
Classifier: Programming Language :: Python :: 3.12
Classifier: Programming Language :: Python :: 3.13
License-File: LICENSE
Dynamic: author
Dynamic: author-email
Dynamic: classifier
Dynamic: description
Dynamic: description-content-type
Dynamic: home-page
Dynamic: keywords
Dynamic: license
Dynamic: license-file
Dynamic: summary
